{
  "menu": "api",
  "children": [
    {
      "path": "48-How to define the mapping relationship of the axes for the combination of line chart and stacked column chart",
      "title": {
        "zh": "48.线图和堆积柱状图组合，如何定义轴的映射关系？",
        "en": "48.How to define the mapping relationship of the axes for the combination of line chart and stacked column chart?"
      }
    },
    {
      "path": "50-How to configure the default selection effect of the legend component",
      "title": {
        "zh": "50.图例组件如何配置默认选中效果？",
        "en": "50.How to configure the default selection effect of the legend component?"
      }
    },
    {
      "path": "51-How does the legend component limit the width of the graph",
      "title": {
        "zh": "51.图例组件如何限制图形的宽度?",
        "en": "51.How does the legend component limit the width of the graph?"
      }
    },
    {
      "path": "52-How to set column width in bar chart",
      "title": {
        "zh": "52.柱状图如何设置柱子宽度?",
        "en": "52.How to set column width in bar chart?"
      }
    },
    {
      "path": "53-How to modify the style of the legend element when the mouse is hovering over the legend",
      "title": {
        "zh": "53.如何实现当鼠标悬浮于图例上时 圆形的图例扩大一圈高亮显示 并且去掉长方形的灰色的背景？",
        "en": "53.How to realize that when the mouse hovers over the legend, the circular legend will be highlighted in a circle and the gray background of the rectangle will be removed?"
      }
    },
    {
      "path": "54-How can we still make data points respond to hover events without displaying point graphics in area chart",
      "title": {
        "zh": "54.面积图，如何不显示 point 图形 的情况下，仍然能让数据点响应 hover 事件？",
        "en": "54.How can we still make data points respond to hover events without displaying point graphics in area chart?"
      }
    },
    {
      "path": "56-How do I set up some lines to follow the left axis, while the others follow the right axis in a line chart",
      "title": {
        "zh": "56.折线图有多条线，如何设置右侧坐标轴，并且某条线是根据右侧坐标轴绘制的？",
        "en": "56.How do I set up some lines to follow the left axis, while the others follow the right axis in a line chart?"
      }
    },
    {
      "path": "57-When hovering over a donut chart, how to configure the style of donut chart",
      "title": {
        "zh": "57.环形图 hover 的时候，如何配置边框的样式？",
        "en": "57.When hovering over a donut chart, how to configure the style of donut chart?"
      }
    },
    {
      "path": "58-How can the background color of the funnel chart's conversion layers be modified",
      "title": {
        "zh": "58.漏斗图转化层的背景颜色如何修改？",
        "en": "58.How can the background color of the funnel chart's conversion layers be modified?"
      }
    },
    {
      "path": "59-How to generate a simplified mini line chart",
      "title": {
        "zh": "59.如何生成一个 mini 折线图？",
        "en": "59.How to generate a simplified mini line chart?"
      }
    },
    {
      "path": "60-How to display the legend title and legend with left-right separation in the same row",
      "title": {
        "zh": "60.如何实现图例的标题和 图例左右分开显示？",
        "en": "60.How to display the legend title and legend with left-right separation in the same row?"
      }
    },
    {
      "path": "61-How to Customize Colors for Different Series in Dual-Axis Chart",
      "title": {
        "zh": "61.线、柱双轴图中，如何自定义不同系列的颜色？",
        "en": "61.How to Customize Colors for Different Series in Dual-Axis Chart?"
      }
    },
    {
      "path": "62-How to disable the default interactive behavior of legends",
      "title": {
        "zh": "62.如何禁用图例的默认交互行为？",
        "en": "62.How to disable the default interactive behavior of legends?"
      }
    },
    {
      "path": "63-How to display the center value when selecting an arc in a pie chart",
      "title": {
        "zh": "63.环形图中心指标能否设置选中时展示？",
        "en": "63.How to display the center value when selecting an arc in a pie chart?"
      }
    },
    {
      "path": "74-How to configure the colors of different line segments in a line chart",
      "title": {
        "zh": "74.折线图如何配置分段颜色？",
        "en": "74.How to configure the colors of different line segments in a line chart?"
      }
    },
    {
      "path": "75-How to configure it to ignore part of the display content",
      "title": {
        "zh": "75.x 轴数据过于密集，如何配置忽略一部分显示内容？",
        "en": "75.How to configure it to ignore part of the display content?"
      }
    },
    {
      "path": "76-How to customize the display text content of the funnel chart",
      "title": {
        "zh": "76.漏斗图如何自定义显示文字内容？",
        "en": "76.How to customize the display text content of the funnel chart?"
      }
    },
    {
      "path": "77-How to customize the colors of bars based on values in a bar chart",
      "title": {
        "zh": "77.柱状图如何根据不同的数值自定义柱子的颜色？",
        "en": "77.How to customize the colors of bars based on values in a bar chart?"
      }
    },
    {
      "path": "78-How to listen to the click event of the histogram to customize the style of the column",
      "title": {
        "zh": "78.如何监听柱状图的点击事件来自定义柱子的样式？",
        "en": "78.How to listen to the click event of the histogram to customize the style of the column?"
      }
    },
    {
      "path": "79-How to change the hover display content when the mouse is moved into the chart area",
      "title": {
        "zh": "79.鼠标移入图表区域，hover 显示内容怎么更换？",
        "en": "79.How to change the hover display content when the mouse is moved into the chart area ?"
      }
    },
    {
      "path": "80-How to customize the length of the pie chart guide line",
      "title": {
        "zh": "80.如何自定义饼图引导线的长度？",
        "en": "80.How to customize the length of the pie chart guide line?"
      }
    },
    {
      "path": "81-How to modify the text color of the percentage of the funnel chart",
      "title": {
        "zh": "81.漏斗图百分比文字颜色如何修改？",
        "en": "81.How to modify the text color of the percentage of the funnel chart?"
      }
    },
    {
      "path": "82-How to configure the transform width of the funnel chart",
      "title": {
        "zh": "82.如何配置漏斗图的转化宽度？",
        "en": "82.How to configure the transform width of the funnel chart?"
      }
    }
  ]
}
